awinrm/__init__.py
awinrm/_version.py
awinrm/encryption.py
awinrm/exceptions.py
awinrm/protocol.py
awinrm/transport.py
awinrm/examples/__init__.py
awinrm/examples/authcheck.py
awinrm/examples/runcmd.py
awinrm/examples/shell.py
awinrm-0.1.1.dist-info/LICENSE
awinrm-0.1.1.dist-info/METADATA
awinrm-0.1.1.dist-info/WHEEL
awinrm-0.1.1.dist-info/entry_points.txt
awinrm-0.1.1.dist-info/top_level.txt
awinrm-0.1.1.dist-info/RECORD
