Metadata-Version: 2.1
Name: awinrm
Version: 0.1.1
Summary: Asynchronous Python library for Windows Remote Management
Home-page: https://github.com/skelsec/awinrm
Author: Tamas Jos
Author-email: info@skelsecprojects.com
License: MIT
Classifier: Programming Language :: Python :: 3.8
Classifier: Programming Language :: Python :: 3.9
Classifier: Programming Language :: Python :: 3.10
Classifier: Programming Language :: Python :: 3.11
Classifier: Programming Language :: Python :: 3.12
Classifier: License :: OSI Approved :: MIT License
Classifier: Operating System :: OS Independent
Requires-Python: >=3.8
License-File: LICENSE
Requires-Dist: unicrypto (>=0.0.11)
Requires-Dist: httpx (>=0.25.0)
Requires-Dist: asyauth (>=0.0.14)
Requires-Dist: aioconsole (>=0.8.1)
Requires-Dist: xmltodict
